{"nodes": [{"id": "c_xampp_htdocs_pos_vendor_setasign_fpdi_src_pdfparser_type_pdfboolean_php", "label": "PdfBoolean.php", "file_type": "code", "source_file": "C:\\xampp\\htdocs\\pos\\vendor\\setasign\\fpdi\\src\\PdfParser\\Type\\PdfBoolean.php", "source_location": "L1"}, {"id": "type_pdfboolean_pdfboolean", "label": "PdfBoolean", "file_type": "code", "source_file": "C:\\xampp\\htdocs\\pos\\vendor\\setasign\\fpdi\\src\\PdfParser\\Type\\PdfBoolean.php", "source_location": "L17"}, {"id": "type_pdfboolean_pdfboolean_create", "label": ".create()", "file_type": "code", "source_file": "C:\\xampp\\htdocs\\pos\\vendor\\setasign\\fpdi\\src\\PdfParser\\Type\\PdfBoolean.php", "source_location": "L25"}, {"id": "type_pdfboolean_pdfboolean_ensure", "label": ".ensure()", "file_type": "code", "source_file": "C:\\xampp\\htdocs\\pos\\vendor\\setasign\\fpdi\\src\\PdfParser\\Type\\PdfBoolean.php", "source_location": "L39"}], "edges": [{"source": "c_xampp_htdocs_pos_vendor_setasign_fpdi_src_pdfparser_type_pdfboolean_php", "target": "type_pdfboolean_pdfboolean", "relation": "contains", "confidence": "EXTRACTED", "source_file": "C:\\xampp\\htdocs\\pos\\vendor\\setasign\\fpdi\\src\\PdfParser\\Type\\PdfBoolean.php", "source_location": "L17", "weight": 1.0}, {"source": "type_pdfboolean_pdfboolean", "target": "type_pdfboolean_pdfboolean_create", "relation": "method", "confidence": "EXTRACTED", "source_file": "C:\\xampp\\htdocs\\pos\\vendor\\setasign\\fpdi\\src\\PdfParser\\Type\\PdfBoolean.php", "source_location": "L25", "weight": 1.0}, {"source": "type_pdfboolean_pdfboolean", "target": "type_pdfboolean_pdfboolean_ensure", "relation": "method", "confidence": "EXTRACTED", "source_file": "C:\\xampp\\htdocs\\pos\\vendor\\setasign\\fpdi\\src\\PdfParser\\Type\\PdfBoolean.php", "source_location": "L39", "weight": 1.0}], "raw_calls": [{"caller_nid": "type_pdfboolean_pdfboolean_ensure", "callee": "PdfType", "is_member_call": false, "source_file": "C:\\xampp\\htdocs\\pos\\vendor\\setasign\\fpdi\\src\\PdfParser\\Type\\PdfBoolean.php", "source_location": "L41"}]}