{"nodes": [{"id": "c_xampp_htdocs_pos_vendor_mpdf_mpdf_tmp_mpdf_ttfontdata_dejavusanscondensed_gdefdata_json", "label": "dejavusanscondensed.GDEFdata.json", "file_type": "code", "source_file": "C:\\xampp\\htdocs\\pos\\vendor\\mpdf\\mpdf\\tmp\\mpdf\\ttfontdata\\dejavusanscondensed.GDEFdata.json", "source_location": "L1"}, {"id": "ttfontdata_dejavusanscondensed_gdefdata_gsub_offset", "label": "GSUB_offset", "file_type": "code", "source_file": "C:\\xampp\\htdocs\\pos\\vendor\\mpdf\\mpdf\\tmp\\mpdf\\ttfontdata\\dejavusanscondensed.GDEFdata.json", "source_location": "L1"}, {"id": "ttfontdata_dejavusanscondensed_gdefdata_gpos_offset", "label": "GPOS_offset", "file_type": "code", "source_file": "C:\\xampp\\htdocs\\pos\\vendor\\mpdf\\mpdf\\tmp\\mpdf\\ttfontdata\\dejavusanscondensed.GDEFdata.json", "source_location": "L1"}, {"id": "ttfontdata_dejavusanscondensed_gdefdata_gsub_length", "label": "GSUB_length", "file_type": "code", "source_file": "C:\\xampp\\htdocs\\pos\\vendor\\mpdf\\mpdf\\tmp\\mpdf\\ttfontdata\\dejavusanscondensed.GDEFdata.json", "source_location": "L1"}, {"id": "ttfontdata_dejavusanscondensed_gdefdata_glyphclassbases", "label": "GlyphClassBases", "file_type": "code", "source_file": "C:\\xampp\\htdocs\\pos\\vendor\\mpdf\\mpdf\\tmp\\mpdf\\ttfontdata\\dejavusanscondensed.GDEFdata.json", "source_location": "L1"}, {"id": "ttfontdata_dejavusanscondensed_gdefdata_glyphclassmarks", "label": "GlyphClassMarks", "file_type": "code", "source_file": "C:\\xampp\\htdocs\\pos\\vendor\\mpdf\\mpdf\\tmp\\mpdf\\ttfontdata\\dejavusanscondensed.GDEFdata.json", "source_location": "L1"}, {"id": "ttfontdata_dejavusanscondensed_gdefdata_glyphclassligatures", "label": "GlyphClassLigatures", "file_type": "code", "source_file": "C:\\xampp\\htdocs\\pos\\vendor\\mpdf\\mpdf\\tmp\\mpdf\\ttfontdata\\dejavusanscondensed.GDEFdata.json", "source_location": "L1"}, {"id": "ttfontdata_dejavusanscondensed_gdefdata_glyphclasscomponents", "label": "GlyphClassComponents", "file_type": "code", "source_file": "C:\\xampp\\htdocs\\pos\\vendor\\mpdf\\mpdf\\tmp\\mpdf\\ttfontdata\\dejavusanscondensed.GDEFdata.json", "source_location": "L1"}, {"id": "ttfontdata_dejavusanscondensed_gdefdata_markglyphsets", "label": "MarkGlyphSets", "file_type": "code", "source_file": "C:\\xampp\\htdocs\\pos\\vendor\\mpdf\\mpdf\\tmp\\mpdf\\ttfontdata\\dejavusanscondensed.GDEFdata.json", "source_location": "L1"}, {"id": "ttfontdata_dejavusanscondensed_gdefdata_markattachmenttype", "label": "MarkAttachmentType", "file_type": "code", "source_file": "C:\\xampp\\htdocs\\pos\\vendor\\mpdf\\mpdf\\tmp\\mpdf\\ttfontdata\\dejavusanscondensed.GDEFdata.json", "source_location": "L1"}, {"id": "ttfontdata_dejavusanscondensed_gdefdata_markattachmenttype_1", "label": "1", "file_type": "code", "source_file": "C:\\xampp\\htdocs\\pos\\vendor\\mpdf\\mpdf\\tmp\\mpdf\\ttfontdata\\dejavusanscondensed.GDEFdata.json", "source_location": "L1"}, {"id": "ttfontdata_dejavusanscondensed_gdefdata_markattachmenttype_2", "label": "2", "file_type": "code", "source_file": "C:\\xampp\\htdocs\\pos\\vendor\\mpdf\\mpdf\\tmp\\mpdf\\ttfontdata\\dejavusanscondensed.GDEFdata.json", "source_location": "L1"}, {"id": "ttfontdata_dejavusanscondensed_gdefdata_markattachmenttype_3", "label": "3", "file_type": "code", "source_file": "C:\\xampp\\htdocs\\pos\\vendor\\mpdf\\mpdf\\tmp\\mpdf\\ttfontdata\\dejavusanscondensed.GDEFdata.json", "source_location": "L1"}, {"id": "ttfontdata_dejavusanscondensed_gdefdata_markattachmenttype_4", "label": "4", "file_type": "code", "source_file": "C:\\xampp\\htdocs\\pos\\vendor\\mpdf\\mpdf\\tmp\\mpdf\\ttfontdata\\dejavusanscondensed.GDEFdata.json", "source_location": "L1"}], "edges": [{"source": "c_xampp_htdocs_pos_vendor_mpdf_mpdf_tmp_mpdf_ttfontdata_dejavusanscondensed_gdefdata_json", "target": "ttfontdata_dejavusanscondensed_gdefdata_gsub_offset", "relation": "contains", "confidence": "EXTRACTED", "source_file": "C:\\xampp\\htdocs\\pos\\vendor\\mpdf\\mpdf\\tmp\\mpdf\\ttfontdata\\dejavusanscondensed.GDEFdata.json", "source_location": "L1", "weight": 1.0}, {"source": "c_xampp_htdocs_pos_vendor_mpdf_mpdf_tmp_mpdf_ttfontdata_dejavusanscondensed_gdefdata_json", "target": "ttfontdata_dejavusanscondensed_gdefdata_gpos_offset", "relation": "contains", "confidence": "EXTRACTED", "source_file": "C:\\xampp\\htdocs\\pos\\vendor\\mpdf\\mpdf\\tmp\\mpdf\\ttfontdata\\dejavusanscondensed.GDEFdata.json", "source_location": "L1", "weight": 1.0}, {"source": "c_xampp_htdocs_pos_vendor_mpdf_mpdf_tmp_mpdf_ttfontdata_dejavusanscondensed_gdefdata_json", "target": "ttfontdata_dejavusanscondensed_gdefdata_gsub_length", "relation": "contains", "confidence": "EXTRACTED", "source_file": "C:\\xampp\\htdocs\\pos\\vendor\\mpdf\\mpdf\\tmp\\mpdf\\ttfontdata\\dejavusanscondensed.GDEFdata.json", "source_location": "L1", "weight": 1.0}, {"source": "c_xampp_htdocs_pos_vendor_mpdf_mpdf_tmp_mpdf_ttfontdata_dejavusanscondensed_gdefdata_json", "target": "ttfontdata_dejavusanscondensed_gdefdata_glyphclassbases", "relation": "contains", "confidence": "EXTRACTED", "source_file": "C:\\xampp\\htdocs\\pos\\vendor\\mpdf\\mpdf\\tmp\\mpdf\\ttfontdata\\dejavusanscondensed.GDEFdata.json", "source_location": "L1", "weight": 1.0}, {"source": "c_xampp_htdocs_pos_vendor_mpdf_mpdf_tmp_mpdf_ttfontdata_dejavusanscondensed_gdefdata_json", "target": "ttfontdata_dejavusanscondensed_gdefdata_glyphclassmarks", "relation": "contains", "confidence": "EXTRACTED", "source_file": "C:\\xampp\\htdocs\\pos\\vendor\\mpdf\\mpdf\\tmp\\mpdf\\ttfontdata\\dejavusanscondensed.GDEFdata.json", "source_location": "L1", "weight": 1.0}, {"source": "c_xampp_htdocs_pos_vendor_mpdf_mpdf_tmp_mpdf_ttfontdata_dejavusanscondensed_gdefdata_json", "target": "ttfontdata_dejavusanscondensed_gdefdata_glyphclassligatures", "relation": "contains", "confidence": "EXTRACTED", "source_file": "C:\\xampp\\htdocs\\pos\\vendor\\mpdf\\mpdf\\tmp\\mpdf\\ttfontdata\\dejavusanscondensed.GDEFdata.json", "source_location": "L1", "weight": 1.0}, {"source": "c_xampp_htdocs_pos_vendor_mpdf_mpdf_tmp_mpdf_ttfontdata_dejavusanscondensed_gdefdata_json", "target": "ttfontdata_dejavusanscondensed_gdefdata_glyphclasscomponents", "relation": "contains", "confidence": "EXTRACTED", "source_file": "C:\\xampp\\htdocs\\pos\\vendor\\mpdf\\mpdf\\tmp\\mpdf\\ttfontdata\\dejavusanscondensed.GDEFdata.json", "source_location": "L1", "weight": 1.0}, {"source": "c_xampp_htdocs_pos_vendor_mpdf_mpdf_tmp_mpdf_ttfontdata_dejavusanscondensed_gdefdata_json", "target": "ttfontdata_dejavusanscondensed_gdefdata_markglyphsets", "relation": "contains", "confidence": "EXTRACTED", "source_file": "C:\\xampp\\htdocs\\pos\\vendor\\mpdf\\mpdf\\tmp\\mpdf\\ttfontdata\\dejavusanscondensed.GDEFdata.json", "source_location": "L1", "weight": 1.0}, {"source": "c_xampp_htdocs_pos_vendor_mpdf_mpdf_tmp_mpdf_ttfontdata_dejavusanscondensed_gdefdata_json", "target": "ttfontdata_dejavusanscondensed_gdefdata_markattachmenttype", "relation": "contains", "confidence": "EXTRACTED", "source_file": "C:\\xampp\\htdocs\\pos\\vendor\\mpdf\\mpdf\\tmp\\mpdf\\ttfontdata\\dejavusanscondensed.GDEFdata.json", "source_location": "L1", "weight": 1.0}, {"source": "ttfontdata_dejavusanscondensed_gdefdata_markattachmenttype", "target": "ttfontdata_dejavusanscondensed_gdefdata_markattachmenttype_1", "relation": "contains", "confidence": "EXTRACTED", "source_file": "C:\\xampp\\htdocs\\pos\\vendor\\mpdf\\mpdf\\tmp\\mpdf\\ttfontdata\\dejavusanscondensed.GDEFdata.json", "source_location": "L1", "weight": 1.0}, {"source": "ttfontdata_dejavusanscondensed_gdefdata_markattachmenttype", "target": "ttfontdata_dejavusanscondensed_gdefdata_markattachmenttype_2", "relation": "contains", "confidence": "EXTRACTED", "source_file": "C:\\xampp\\htdocs\\pos\\vendor\\mpdf\\mpdf\\tmp\\mpdf\\ttfontdata\\dejavusanscondensed.GDEFdata.json", "source_location": "L1", "weight": 1.0}, {"source": "ttfontdata_dejavusanscondensed_gdefdata_markattachmenttype", "target": "ttfontdata_dejavusanscondensed_gdefdata_markattachmenttype_3", "relation": "contains", "confidence": "EXTRACTED", "source_file": "C:\\xampp\\htdocs\\pos\\vendor\\mpdf\\mpdf\\tmp\\mpdf\\ttfontdata\\dejavusanscondensed.GDEFdata.json", "source_location": "L1", "weight": 1.0}, {"source": "ttfontdata_dejavusanscondensed_gdefdata_markattachmenttype", "target": "ttfontdata_dejavusanscondensed_gdefdata_markattachmenttype_4", "relation": "contains", "confidence": "EXTRACTED", "source_file": "C:\\xampp\\htdocs\\pos\\vendor\\mpdf\\mpdf\\tmp\\mpdf\\ttfontdata\\dejavusanscondensed.GDEFdata.json", "source_location": "L1", "weight": 1.0}]}