{"nodes": [{"id": "c_xampp_htdocs_pos_scratch_merge_countries_py", "label": "merge_countries.py", "file_type": "code", "source_file": "C:\\xampp\\htdocs\\pos\\scratch\\merge_countries.py", "source_location": "L1"}, {"id": "scratch_merge_countries_parse_file1", "label": "parse_file1()", "file_type": "code", "source_file": "C:\\xampp\\htdocs\\pos\\scratch\\merge_countries.py", "source_location": "L7"}, {"id": "scratch_merge_countries_parse_file2", "label": "parse_file2()", "file_type": "code", "source_file": "C:\\xampp\\htdocs\\pos\\scratch\\merge_countries.py", "source_location": "L25"}], "edges": [{"source": "c_xampp_htdocs_pos_scratch_merge_countries_py", "target": "re", "relation": "imports", "context": "import", "confidence": "EXTRACTED", "source_file": "C:\\xampp\\htdocs\\pos\\scratch\\merge_countries.py", "source_location": "L1", "weight": 1.0}, {"source": "c_xampp_htdocs_pos_scratch_merge_countries_py", "target": "scratch_merge_countries_parse_file1", "relation": "contains", "confidence": "EXTRACTED", "source_file": "C:\\xampp\\htdocs\\pos\\scratch\\merge_countries.py", "source_location": "L7", "weight": 1.0}, {"source": "c_xampp_htdocs_pos_scratch_merge_countries_py", "target": "scratch_merge_countries_parse_file2", "relation": "contains", "confidence": "EXTRACTED", "source_file": "C:\\xampp\\htdocs\\pos\\scratch\\merge_countries.py", "source_location": "L25", "weight": 1.0}], "raw_calls": [{"caller_nid": "scratch_merge_countries_parse_file1", "callee": "open", "is_member_call": false, "source_file": "C:\\xampp\\htdocs\\pos\\scratch\\merge_countries.py", "source_location": "L9"}, {"caller_nid": "scratch_merge_countries_parse_file1", "callee": "read", "is_member_call": true, "source_file": "C:\\xampp\\htdocs\\pos\\scratch\\merge_countries.py", "source_location": "L10"}, {"caller_nid": "scratch_merge_countries_parse_file1", "callee": "findall", "is_member_call": true, "source_file": "C:\\xampp\\htdocs\\pos\\scratch\\merge_countries.py", "source_location": "L12"}, {"caller_nid": "scratch_merge_countries_parse_file1", "callee": "append", "is_member_call": true, "source_file": "C:\\xampp\\htdocs\\pos\\scratch\\merge_countries.py", "source_location": "L14"}, {"caller_nid": "scratch_merge_countries_parse_file2", "callee": "open", "is_member_call": false, "source_file": "C:\\xampp\\htdocs\\pos\\scratch\\merge_countries.py", "source_location": "L27"}, {"caller_nid": "scratch_merge_countries_parse_file2", "callee": "read", "is_member_call": true, "source_file": "C:\\xampp\\htdocs\\pos\\scratch\\merge_countries.py", "source_location": "L28"}, {"caller_nid": "scratch_merge_countries_parse_file2", "callee": "findall", "is_member_call": true, "source_file": "C:\\xampp\\htdocs\\pos\\scratch\\merge_countries.py", "source_location": "L30"}]}