{"nodes": [{"id": "c_xampp_htdocs_pos_vendor_setasign_fpdi_src_pdfreader_pageboundaries_php", "label": "PageBoundaries.php", "file_type": "code", "source_file": "C:\\xampp\\htdocs\\pos\\vendor\\setasign\\fpdi\\src\\PdfReader\\PageBoundaries.php", "source_location": "L1"}, {"id": "pdfreader_pageboundaries_pageboundaries", "label": "PageBoundaries", "file_type": "code", "source_file": "C:\\xampp\\htdocs\\pos\\vendor\\setasign\\fpdi\\src\\PdfReader\\PageBoundaries.php", "source_location": "L17"}, {"id": "pdfreader_pageboundaries_pageboundaries_isvalidname", "label": ".isValidName()", "file_type": "code", "source_file": "C:\\xampp\\htdocs\\pos\\vendor\\setasign\\fpdi\\src\\PdfReader\\PageBoundaries.php", "source_location": "L91"}], "edges": [{"source": "c_xampp_htdocs_pos_vendor_setasign_fpdi_src_pdfreader_pageboundaries_php", "target": "pdfreader_pageboundaries_pageboundaries", "relation": "contains", "confidence": "EXTRACTED", "source_file": "C:\\xampp\\htdocs\\pos\\vendor\\setasign\\fpdi\\src\\PdfReader\\PageBoundaries.php", "source_location": "L17", "weight": 1.0}, {"source": "pdfreader_pageboundaries_pageboundaries", "target": "pdfreader_pageboundaries_pageboundaries_isvalidname", "relation": "method", "confidence": "EXTRACTED", "source_file": "C:\\xampp\\htdocs\\pos\\vendor\\setasign\\fpdi\\src\\PdfReader\\PageBoundaries.php", "source_location": "L91", "weight": 1.0}], "raw_calls": [{"caller_nid": "pdfreader_pageboundaries_pageboundaries_isvalidname", "callee": "\\in_array", "is_member_call": false, "source_file": "C:\\xampp\\htdocs\\pos\\vendor\\setasign\\fpdi\\src\\PdfReader\\PageBoundaries.php", "source_location": "L93"}]}